setuptools_sky
