Metadata-Version: 1.1
Name: setuptools-sky
Version: 0.1.7
Summary: the blessed package to manage your versions by scm tags
Home-page: https://bitbucket.org/sekomy/setuptools-sky
Author: Sekom Yazilim
Author-email: info@sekomyazilim.com.tr
License: MIT
Platform: UNKNOWN
Classifier: Development Status :: 4 - Beta
Classifier: Intended Audience :: Developers
Classifier: License :: OSI Approved :: MIT License
Classifier: Programming Language :: Python
Classifier: Programming Language :: Python :: 3
Classifier: Programming Language :: Python :: 2.6
Classifier: Programming Language :: Python :: 2.7
Classifier: Programming Language :: Python :: 3.3
Classifier: Programming Language :: Python :: 3.4
Classifier: Programming Language :: Python :: 3.5
Classifier: Programming Language :: Python :: 3.6
Classifier: Topic :: Software Development :: Libraries
Classifier: Topic :: Software Development :: Version Control
Classifier: Topic :: System :: Software Distribution
Classifier: Topic :: Utilities
